.clang-format
.flake8
.gitignore
.gitmodules
CHANGELOG.md
CODEOWNERS
CODE_OF_CONDUCT
Dockerfile
Dockerfile-cuda
Dockerfile-embedded
LICENSE
MANIFEST.in
Makefile
README.md
__init__.py
description.txt
packages.txt
setup.py
./src/opendr/__init__.py
./src/opendr/_setup.py
./src/opendr/_version.py
./src/opendr/control/__init__.py
./src/opendr/engine/__init__.py
./src/opendr/engine/constants.py
./src/opendr/engine/data.py
./src/opendr/engine/datasets.py
./src/opendr/engine/example_learner.py
./src/opendr/engine/learners.py
./src/opendr/engine/target.py
./src/opendr/perception/__init__.py
./src/opendr/perception/binary_high_resolution/README.md
./src/opendr/perception/binary_high_resolution/__init__.py
./src/opendr/perception/binary_high_resolution/binary_high_resolution_learner.py
./src/opendr/perception/binary_high_resolution/dependencies.ini
./src/opendr/perception/binary_high_resolution/utils/__init__.py
./src/opendr/perception/binary_high_resolution/utils/architectures.py
./src/opendr/perception/binary_high_resolution/utils/high_resolution_loader.py
./src/opendr/perception/binary_high_resolution/utils/utils.py
./src/opendr/planning/__init__.py
./src/opendr/simulation/__init__.py
./src/opendr/utils/__init__.py
./src/opendr_toolkit_binary_high_resolution.egg-info/PKG-INFO
./src/opendr_toolkit_binary_high_resolution.egg-info/SOURCES.txt
./src/opendr_toolkit_binary_high_resolution.egg-info/dependency_links.txt
./src/opendr_toolkit_binary_high_resolution.egg-info/requires.txt
./src/opendr_toolkit_binary_high_resolution.egg-info/top_level.txt
src/opendr/_setup.py
src/opendr/_version.py
src/opendr/perception/binary_high_resolution/README.md
src/opendr/perception/binary_high_resolution/__init__.py
src/opendr/perception/binary_high_resolution/binary_high_resolution_learner.py
src/opendr/perception/binary_high_resolution/dependencies.ini
src/opendr/perception/binary_high_resolution/utils/__init__.py
src/opendr/perception/binary_high_resolution/utils/architectures.py
src/opendr/perception/binary_high_resolution/utils/high_resolution_loader.py
src/opendr/perception/binary_high_resolution/utils/utils.py